{
  "common": {
    "ok": "OK",
    "cancel": "Mégse",
    "close": "Bezárás",
    "save": "Mentés",
    "delete": "Törlés",
    "update": "Frissítés",
    "discard": "Elvetés",
    "execute": "Végrehajtás",
    "loading": "Betöltés folyamatban",
    "loadingEllipsis": "Betöltés...",
    "next": "Következő",
    "previous": "Előző",
    "yes": "Igen",
    "no": "Nem",
    "result": "Eredmény",
    "learnMore": "További információ",
    "getStarted": "Első lépések",
    "retry": "Újrapróbálkozás",
    "apply": "Alkalmaz",
    "refresh": "Frissítés",
    "copy": "Másolás",
    "create": "Létrehozás",
    "confirm": "Megerősítés",
    "open": "Megnyitás",
    "rename": "Átnevezés",
    "download": "Letöltés",
    "upload": "Feltöltés",
    "connect": "Kapcsolódás",
    "remove": "Eltávolítás",
    "load": "Betöltés",
    "publish": "Közzététel",
    "browse": "Tallózás",
    "increaseValueBy1": "Érték növelése 1-gyel",
    "decreaseValueBy1": "Érték csökkentése 1-gyel"
  },
  "splashScreen": {
    "title": {
      "default": "Üdvözli az Azure Cosmos DB",
      "postgres": "Üdvözli az Azure Cosmos DB for PostgreSQL",
      "vcoreMongo": "Üdvözli az Azure DocumentDB (MongoDB-kompatibilitással)"
    },
    "subtitle": {
      "default": "Globálisan elosztott, többmodelles adatbázis-szolgáltatás bármilyen mérethez",
      "getStarted": "Ismerje meg a minta adathalmazok, a dokumentáció és a további eszközök használatának első lépéseit."
    },
    "quickStart": {
      "title": "A Rövid útmutató elindítása",
      "description": "Gyors üzembe helyezési oktatóanyag indítása a mintaadatok használatának első lépéseihez"
    },
    "newCollection": {
      "title": "Új {{collectionName}}",
      "description": "Új tároló létrehozása a tároláshoz és az átviteli sebességhez"
    },
    "samplesGallery": {
      "title": "Azure Cosmos DB minták gyűjteménye",
      "description": "Fedezzen fel skálázható, intelligens alkalmazásmintákat. Próbálja ki most, hogy lássa, milyen gyorsan válthat a fogalmakról a kódolásra a Cosmos DB használatával"
    },
    "connectCard": {
      "title": "Csatlakozás",
      "description": "Inkább a saját eszközeit használná? Találja meg a kapcsolati sztringet, amire a csatlakozáshoz szüksége van",
      "pgAdmin": {
        "title": "Kapcsolódás pgAdmin használatával",
        "description": "Előnyben részesíti a pgAdmin-t? Itt találja a kapcsolati sztringeket"
      },
      "vsCode": {
        "title": "Csatlakozás VS Code használatával",
        "description": "MongoDB- és DocumentDB-fürtök lekérdezése és kezelése Visual Studio Code-ban"
      }
    },
    "shell": {
      "postgres": {
        "title": "PostgreSQL Shell",
        "description": "Tábla létrehozása és az adatok kezelése a PostgreSQL shell felület használatával"
      },
      "vcoreMongo": {
        "title": "Mongo shell",
        "description": "Gyűjtemény létrehozása és az adatok kezelése a MongoDB felületének használatával"
      }
    },
    "teachingBubble": {
      "newToPostgres": {
        "headline": "Most ismerkedik a Cosmos DB PGSQL-lel?",
        "body": "Üdvözöljük! Ha most ismerkedik a Cosmos DB PGSQL használatával és segítségre van szüksége az első lépésekhez, itt találhat mintaadatokat, lekérdezéseket."
      },
      "resetPassword": {
        "headline": "Jelszó létrehozása",
        "body": "Ha még nem módosította a jelszavát, módosítsa most."
      },
      "coachMark": {
        "headline": "Kezdje a(z) {{collectionName}} mintával",
        "body": "Végigvezetjük egy mintatároló létrehozásán mintaadatokkal, majd bemutatjuk az adatkezelőt. A bemutató indítását meg is szakíthatja, és felfedezheti önállóan"
      }
    },
    "sections": {
      "recents": "Legutóbbiak",
      "clearRecents": "Legutóbbiak törlése",
      "top3": "A 3 legfontosabb tudnivaló",
      "learningResources": "Tanulási források",
      "nextSteps": "Következő lépések",
      "tipsAndLearnMore": "Tippek és további információ",
      "notebook": "Jegyzetfüzet",
      "needHelp": "Segítségre van szüksége?"
    },
    "top3Items": {
      "sql": {
        "advancedModeling": {
          "title": "Speciális modellezési minták",
          "description": "Ismerjen meg speciális stratégiákat z adatbázis optimalizálásához."
        },
        "partitioning": {
          "title": "Ajánlott particionálási eljárások",
          "description": "Tudja meg, hogyan alkalmazhat adatmodellt és particionálási stratégiákat."
        },
        "resourcePlanning": {
          "title": "Az erőforrás-követelmények megtervezése",
          "description": "Ismerkedjen meg a különböző konfigurációs lehetőségekkel."
        }
      },
      "mongo": {
        "whatIsMongo": {
          "title": "Mi az a MongoDB API?",
          "description": "Ismerje meg az Azure Cosmos DB for MongoDB használatát és funkcióit."
        },
        "features": {
          "title": "Funkciók és szintaxis",
          "description": "Az előnyök és funkciók felfedezése"
        },
        "migrate": {
          "title": "Adatok áttelepítése",
          "description": "Áttelepítés előtti lépések az adatok áthelyezéséhez"
        }
      },
      "cassandra": {
        "buildJavaApp": {
          "title": "Java-alkalmazás létrehozása",
          "description": "Java-alkalmazás létrehozása SDK használatával."
        },
        "partitioning": {
          "title": "Ajánlott particionálási eljárások",
          "description": "Ismerje meg a particionálás működését."
        },
        "requestUnits": {
          "title": "Kérelemegységek (RU-k)",
          "description": "A kérelemegység-díjak ismertetése."
        }
      },
      "gremlin": {
        "dataModeling": {
          "title": "Adatmodellezés",
          "description": "Gráfadatok modellezésével kapcsolatos javaslatok"
        },
        "partitioning": {
          "title": "Ajánlott particionálási eljárások",
          "description": "Ismerje meg a particionálás működését"
        },
        "queryData": {
          "title": "Adatok lekérdezése",
          "description": "Adatok lekérdezése a Gremlinnel"
        }
      },
      "tables": {
        "whatIsTable": {
          "title": "Mi a tábla-API?",
          "description": "Ismerje meg az Azure Cosmos DB for Table használatát és funkcióit"
        },
        "migrate": {
          "title": "Adatok áttelepítése",
          "description": "Ismerje meg, hogyan telepítheti át az adatait"
        },
        "faq": {
          "title": "Azure Cosmos DB for Table GYIK",
          "description": "Gyakori kérdések a Azure Cosmos DB for Table kapcsán"
        }
      }
    },
    "learningResources": {
      "shortcuts": {
        "title": "Adatkezelő billentyűparancsok",
        "description": "Ismerje meg a Data Explorer navigálásához használható billentyűparancsokat."
      },
      "liveTv": {
        "title": "Az alapok megismerése",
        "description": "Nézze meg Azure Cosmos DB élő tv-műsor bevezető videóit és videóit."
      },
      "sql": {
        "sdk": {
          "title": "Az SDK használatának első lépései",
          "description": "Tudnivalók a Azure Cosmos DB SDK-ról."
        },
        "migrate": {
          "title": "Adatok áttelepítése",
          "description": "Adatok áttelepítése Azure-szolgáltatásokkal és nyílt forráskódú megoldásokkal."
        }
      },
      "mongo": {
        "nodejs": {
          "title": "Alkalmazás készítése Node.js használatával",
          "description": "Hozzon létre egy Node.js alkalmazást."
        },
        "gettingStarted": {
          "title": "Első lépéseket ismertető útmutató",
          "description": "Első lépésként ismerkedjen meg az alapokkal."
        }
      },
      "cassandra": {
        "createContainer": {
          "title": "Tároló létrehozása",
          "description": "Ismerje meg a tárolók létrehozásának lehetőségeit."
        },
        "throughput": {
          "title": "Átviteli sebesség kiosztása",
          "description": "Útmutató az átviteli sebesség konfigurálásához."
        }
      },
      "gremlin": {
        "getStarted": {
          "title": "Első lépések ",
          "description": "Létrehozás, lekérdezés és bejárás a Gremlin-konzol használatával"
        },
        "importData": {
          "title": "Gráfadatok importálása",
          "description": "Tömeges betöltési adatok megismerése a BulkExecutor használatával"
        }
      },
      "tables": {
        "dotnet": {
          "title": ".NET-alkalmazás létrehozása",
          "description": "Az Azure Cosmos DB for Table elérése .NET-alkalmazásból."
        },
        "java": {
          "title": "Java-alkalmazás létrehozása",
          "description": "Azure Cosmos DB for Table alkalmazás létrehozása Java SDK használatával "
        }
      }
    },
    "nextStepItems": {
      "postgres": {
        "dataModeling": "Adatmodellezés",
        "distributionColumn": "Terjesztési oszlop kiválasztása",
        "buildApps": "Alkalmazások készítése Python/Java/Django használatával"
      },
      "vcoreMongo": {
        "migrateData": "Adatok áttelepítése",
        "vectorSearch": "AI-alkalmazások létrehozása vektor keresés használatával",
        "buildApps": "Alkalmazások létrehozása a Nodejs használatával"
      }
    },
    "learnMoreItems": {
      "postgres": {
        "performanceTuning": "Teljesítményhangolás",
        "diagnosticQueries": "Hasznos diagnosztikai lekérdezések",
        "sqlReference": "Elosztott SQL-referencia"
      },
      "vcoreMongo": {
        "vectorSearch": "Vektor keresés",
        "textIndexing": "Szövegindexelés",
        "troubleshoot": "A leggyakoribb problémák elhárítása"
      }
    },
    "fabric": {
      "buildTitle": "Adatbázis létrehozása",
      "useTitle": "Saját adatbázis használata",
      "newContainer": {
        "title": "Új tároló",
        "description": "Céltároló létrehozása az adatok tárolásához"
      },
      "sampleData": {
        "title": "Mintaadatok",
        "description": "Mintaadatok betöltése az adatbázisban"
      },
      "sampleVectorData": {
        "title": "Mintavektoradatok",
        "description": "Mintavektoradatok betöltése text-embedding-ada-002 használatával"
      },
      "appDevelopment": {
        "title": "Alkalmazásfejlesztés",
        "description": "Kezdje itt az alkalmazások SDK-val történő létrehozásához"
      },
      "sampleGallery": {
        "title": "Mintagyűjtemény",
        "description": "Valós, teljes körű minták"
      }
    },
    "sampleDataDialog": {
      "title": "Mintaadatok",
      "startButton": "Kezdés",
      "createPrompt": "Hozzon létre egy {{containerName}} tárolót, és importálja a mintaadatokat. Ez több percet is igénybe vehet.",
      "creatingContainer": "A(z) {{containerName}} tároló létrehozása...",
      "importingData": "Adatok importálása a következőbe: {{containerName}}...",
      "success": "A(z) {{containerName}} sikeresen létrehozva mintaadatokkal.",
      "errorContainerExists": "A(z) {{containerName}} tároló már létezik a(z) {{databaseName}} adatbázisban. Törölje, majd próbálkozzon újra.",
      "errorCreateContainer": "Nem sikerült létrehozni a tárolót: {{error}}",
      "errorImportData": "Nem sikerült az adatok importálása: {{error}}"
    }
  },
  "contextMenu": {
    "newContainer": "Új {{containerName}}",
    "restoreContainer": "{{containerName}} visszaállítása",
    "deleteDatabase": "{{databaseName}} törlése",
    "deleteContainer": "{{containerName}} törlése",
    "newSqlQuery": "Új SQL-lekérdezés",
    "newQuery": "Új lekérdezés",
    "openMongoShell": "Mongo-felület megnyitása",
    "newShell": "Új felület",
    "openCassandraShell": "Cassandra-felület megnyitása",
    "newStoredProcedure": "Új tárolt eljárás",
    "newUdf": "Új UDF",
    "newTrigger": "Új eseményindító",
    "deleteStoredProcedure": "Tárolt eljárás törlése",
    "deleteTrigger": "Trigger törlése",
    "deleteUdf": "Felhasználó által definiált függvény törlése"
  },
  "tabs": {
    "documents": {
      "newItem": "Új elem",
      "newDocument": "Új dokumentum",
      "uploadItem": "Elem feltöltése",
      "applyFilter": "Szűrő alkalmazása",
      "unsavedChanges": "Nem mentett módosítások",
      "unsavedChangesMessage": "A nem mentett módosítások elvesznek. Folytatja?",
      "createDocumentFailed": "A dokumentum létrehozása nem sikerült",
      "updateDocumentFailed": "A dokumentum frissítése nem sikerült",
      "documentDeleted": "A dokumentum törlése sikerült.",
      "deleteDocumentDialogTitle": "Dokumentum törlése",
      "deleteDocumentsDialogTitle": "Dokumentumok törlése",
      "throttlingError": "Néhány dokumentum törlése sebességkorlátozási hiba miatt nem sikerült. Próbálkozzon újra később. A jövőben a hasonló esetek elkerülése érdekében fontolja meg a tároló vagy az adatbázis átviteli sebességének növelését.",
      "deleteFailed": "Nem sikerült törölni a dokumentum(oka)t ({{error}})",
      "missingShardProperty": "A dokumentumból hiányzik a szegmens tulajdonság: {{partitionKeyProperty}}",
      "refreshGridFailed": "Nem sikerült frissíteni a dokumentumrácsot",
      "confirmDelete": "Biztosan törli a következőt: {{documentName}}?",
      "confirmDeleteTitle": "Törlés megerősítése",
      "selectedItems": "a kijelölt {{count}} elemek",
      "selectedItem": "a kijelölt elem",
      "selectedDocuments": "a kijelölt {{count}} dokumentumok",
      "selectedDocument": "a kijelölt dokumentum",
      "deleteDocumentFailedLog": "Nem sikerült törölni a(z) {{statusCode}} állapotkóddal rendelkező {{documentId}} dokumentumot",
      "deleteSuccessLog": "{{count}} dokumentum törlése sikerült",
      "deleteThrottledLog": "Nem sikerült törölni {{count}} dokumentumot a „Túl nagy kérés” (429) hiba miatt. Újrapróbálkozás...",
      "missingShardKeyLog": "Nem sikerült menteni az új dokumentumot: a dokumentum szegmenskulcsa nincs megadva",
      "filterTooltip": "Írjon be egy lekérdezési predikátumot, vagy válasszon egyet a listából.",
      "loadMore": "Továbbiak betöltése",
      "documentEditor": "Dokumentumszerkesztő",
      "savedFilters": "Mentett szűrők",
      "defaultFilters": "Alapértelmezett szűrők",
      "abort": "Megszakítás",
      "deletingDocuments": "{{count}} dokumentum törlése",
      "deletedDocumentsSuccess": "{{count}} dokumentum törlése sikerült.",
      "deleteAborted": "A dokumentum(ok) törlése megszakadt.",
      "failedToDeleteDocuments": "Nem sikerült törölni {{count}} dokumentumot.",
      "requestTooLargeBase": "Néhány törlési kérés sikertelen volt a „Túl nagy kérés” kivétel (429) miatt",
      "retriedSuccessfully": "de a rendszer sikeresen újrapróbálkozott.",
      "retryingNow": "Újrapróbálkozás most.",
      "increaseThroughputTip": "A jövőben a hasonló esetek elkerülése érdekében fontolja meg a tároló vagy az adatbázis átviteli sebességének növelését.",
      "numberOfSelectedDocuments": "A kijelölt dokumentumok száma: {{count}}",
      "mongoFilterPlaceholder": "Írjon be egy lekérdezési feltételt (pl. {\"id\":\"foo\"}), válasszon egyet a legördülő listából, vagy hagyja üresen az összes dokumentum lekérdezéséhez.",
      "sqlFilterPlaceholder": "Írjon be egy lekérdezési feltételt (pl. WHERE c.id=\"1\"), válasszon egyet a legördülő listából, vagy hagyja üresen az összes dokumentum lekérdezéséhez.",
      "error": "Hiba",
      "warning": "Figyelmeztetés"
    },
    "query": {
      "executeQuery": "Lekérdezés végrehajtása",
      "executeSelection": "Kijelölés végrehajtása",
      "saveQuery": "Lekérdezés mentése",
      "downloadQuery": "Lekérdezés letöltése",
      "cancelQuery": "Lekérdezés megszakítása",
      "openSavedQueries": "Mentett lekérdezések megnyitása",
      "vertical": "Ágazat",
      "horizontal": "Vízszintes",
      "view": "Megtekintés",
      "editingQuery": "Lekérdezés szerkesztése"
    },
    "storedProcedure": {
      "id": "Tárolt eljárás azonosítója",
      "idPlaceholder": "Adja meg az új tárolt eljárás azonosítóját",
      "idAriaLabel": "Tárolt eljárás azonosítója",
      "body": "Tárolt eljárás törzse",
      "bodyAriaLabel": "Tárolt eljárás törzse",
      "successfulExecution": "A tárolt eljárás sikeres végrehajtása",
      "resultAriaLabel": "Tárolt eljárás végrehajtásának eredménye",
      "logsAriaLabel": "Tárolt eljárásnaplók végrehajtása",
      "errors": "Hibák:",
      "errorDetailsAriaLabel": "Hiba részleteinek hivatkozása",
      "moreDetails": "További részletek",
      "consoleLogTab": "console.log"
    },
    "trigger": {
      "id": "Eseményindító azonosítója",
      "idPlaceholder": "Adja meg az új eseményindító azonosítóját",
      "type": "Eseményindító típusa",
      "operation": "Triggerművelet",
      "body": "Triggertörzs",
      "bodyAriaLabel": "Eseményindító törzse",
      "pre": "Előzetes",
      "post": "Közzététel",
      "all": "Az összes",
      "operationCreate": "Létrehozás",
      "operationDelete": "Törlés",
      "operationReplace": "Lecserélés"
    },
    "udf": {
      "id": "Felhasználó által meghatározott függvény azonosítója",
      "idPlaceholder": "Adja meg az új, felhasználó által meghatározott függvény azonosítóját",
      "body": "Felhasználó által meghatározott függvény törzse",
      "bodyAriaLabel": "Felhasználó által meghatározott függvény törzse"
    },
    "conflicts": {
      "unsavedChanges": "Nem mentett módosítások",
      "changesWillBeLost": "Az összes módosítás elveszik. Folytatja?",
      "resolveConflictFailed": "Az ütközés feloldása meghiúsult",
      "deleteConflictFailed": "Az ütközés törlése nem sikerült",
      "refreshGridFailed": "Nem sikerült frissíteni a dokumentumrácsot"
    },
    "mongoShell": {
      "title": "Mongo-felület"
    }
  },
  "panes": {
    "deleteDatabase": {
      "panelTitle": "A(z) {{databaseName}} törlése",
      "warningMessage": "Figyelem! A végrehajtani kívánt művelet nem vonható vissza. Ha folytatja, úgy véglegesen törli az erőforrást és annak minden gyermekerőforrását.",
      "confirmPrompt": "Megerősítés a(z) {{databaseName}}-azonosító (név) beírásával",
      "inputMismatch": "A(z) {{databaseName}} bemenet {{input}} neve nem egyezik a kijelölt {{databaseName}} {{selectedId}} értékével",
      "feedbackTitle": "Segítsen a Azure Cosmos DB továbbfejlesztésében!",
      "feedbackReason": "Mi a(z) {{databaseName}} törlésének oka?"
    },
    "deleteCollection": {
      "panelTitle": "A(z) {{collectionName}} törlése",
      "confirmPrompt": "Megerősítés a(z) {{collectionName}} azonosítójának beírásával",
      "inputMismatch": "A(z) {{input}} bemeneti azonosító nem egyezik a kijelölt {{selectedId}} értékével",
      "feedbackTitle": "Segítsen a Azure Cosmos DB továbbfejlesztésében!",
      "feedbackReason": "Mi a(z) {{collectionName}} törlésének oka?"
    },
    "addDatabase": {
      "databaseLabel": "{{suffix}} adatbázis",
      "databaseIdLabel": "Adatbázis-azonosító",
      "keyspaceIdLabel": "Kulcstér azonosítója",
      "databaseIdPlaceholder": "Írjon be egy új {{databaseLabel}}-azonosítót",
      "databaseTooltip": "A(z) {{databaseLabel}} egy vagy több {{collectionsLabel}} logikai tárolója",
      "shareThroughput": "Átviteli sebesség megosztása az összes {{collectionsLabel}} között",
      "shareThroughputTooltip": "A(z) {{databaseLabel}} szinten kiépített átviteli sebesség meg lesz osztva az összes {{collectionsLabel}} között a(z) {{databaseLabel}} keretein belül.",
      "greaterThanError": "Az Autopilot átviteli sebességéhez olyan értéket adjon meg, ami nagyobb, mint {{minValue}}",
      "acknowledgeSpendError": "Nyugtázza a becsült {{period}} ráfordítást.",
      "acknowledgeSpendErrorMonthly": "Please acknowledge the estimated monthly spend.",
      "acknowledgeSpendErrorDaily": "Please acknowledge the estimated daily spend.",
      "provisionSharedThroughputTitle": "Provision shared throughput",
      "provisionThroughputLabel": "Provision throughput"
    },
    "addCollection": {
      "createNew": "Új létrehozása",
      "useExisting": "Meglévő használata",
      "databaseTooltip": "Az adatbázis hasonló a névtérhez. Ez a(z) {{collectionName}}-készlet felügyeleti egysége.",
      "shareThroughput": "Átviteli sebesség megosztása az összes {{collectionName}} között",
      "shareThroughputTooltip": "Az adatbázis szintjén konfigurált átviteli sebesség az összes {{collectionName}} között meg lesz osztva az adatbázisban.",
      "collectionIdLabel": "{{collectionName}}-azonosító",
      "collectionIdTooltip": "A(z) {{collectionName}} egyedi azonosítója, amelyet a rendszer az azonosítóalapú útválasztás során használ a REST-ben és az összes SDK-ban.",
      "collectionIdPlaceholder": "például {{collectionName}}1",
      "collectionIdAriaLabel": "{{collectionName}}-azonosító, {{collectionName}}1. példa",
      "existingDatabaseAriaLabel": "Meglévő {{databaseName}}-azonosító kiválasztása",
      "existingDatabasePlaceholder": "Meglévő {{databaseName}}-azonosító kiválasztása",
      "indexing": "Indexelés",
      "turnOnIndexing": "Indexelés bekapcsolása",
      "automatic": "Automatikus",
      "turnOffIndexing": "Indexelés kikapcsolása",
      "off": "Ki",
      "sharding": "Horizontális skálázás",
      "shardingTooltip": "A horizontálisan skálázott gyűjtemények több replikakészletre (szegmensre) osztják fel az adatokat a korlátlan méretezhetőség érdekében. A horizontálisan skálázott gyűjtemények esetében ki kell választani egy szegmenskulcsot (mezőt) az adatok egyenletes elosztásához.",
      "unsharded": "Horizontálisan nem skálázott",
      "unshardedLabel": "Horizontálisan nem skálázott (20 GB-os korlát)",
      "sharded": "Horizontálisan skálázott",
      "addPartitionKey": "Hierarchikus partíciókulcs hozzáadása",
      "hierarchicalPartitionKeyInfo": "Ez a funkció lehetővé teszi, hogy akár három kulcsszinttel particionálja az adatokat a jobb adatelosztás érdekében. A használatához .NET V3, Java V4 SDK vagy előzetes verziójú JavaScript V3 SDK szükséges.",
      "provisionDedicatedThroughput": "Dedikált átviteli sebesség kiépítése ehhez: {{collectionName}}",
      "provisionDedicatedThroughputTooltip": "Opcionálisan dedikált átviteli sebességet is kioszthat egy {{collectionName}} elemhez egy kiépített átviteli sebességgel rendelkező adatbázison belül. Ez a dedikált átviteli sebesség-mennyiség nem lesz megosztva a kulcstér más {{collectionNamePlural}} elemeivel, és nem számít bele az adatbázis kiosztott átviteli sebességbe. Ezt az átviteli sebességet az adatbázis szintjén kiosztott átviteli sebességen felül számlázzuk.",
      "uniqueKeysPlaceholderMongo": "Vesszővel elválasztott elérési utak, például firstName,address.zipCode",
      "uniqueKeysPlaceholderSql": "Vesszővel elválasztott elérési utak, például /firstName,/address/zipCode",
      "addUniqueKey": "Egyedi kulcs hozzáadása",
      "enableAnalyticalStore": "Elemzési tár engedélyezése",
      "disableAnalyticalStore": "Elemzési tár letiltása",
      "on": "Be",
      "analyticalStoreSynapseLinkRequired": "Azure Synapse Link szükséges a(z) {{collectionName}} elemzési tár létrehozásához. Engedélyezze a Synapse Link szolgáltatást ehhez a Cosmos DB fiókhoz.",
      "enable": "Engedélyezés",
      "containerVectorPolicy": "Tárolóvektor-házirend",
      "containerFullTextSearchPolicy": "Tároló teljes szöveges keresési szabályzata",
      "advanced": "Speciális",
      "mongoIndexingTooltip": "Az _id mező alapértelmezés szerint indexelve van. Egy helyettesítő karakteres index létrehozása az összes mezőhöz optimalizálja a lekérdezéseket; ez ajánlott a fejlesztéshez.",
      "createWildcardIndex": "Helyettesítő karakteres index létrehozása az összes mezőhöz",
      "legacySdkCheckbox": "Az alkalmazásom egy régebbi Cosmos .NET- vagy Java SDK-verziót (.NET V1 vagy Java V2) használ",
      "legacySdkInfo": "A régebbi SDK-kkal való kompatibilitás biztosítása érdekében a létrehozott tároló egy örökölt particionálási sémát fog használni, amely legfeljebb 101 bájt méretű partíciókulcs-értékeket támogat. Ha ez engedélyezve van, nem használhat hierarchikus partíciókulcsokat.",
      "indexingOnInfo": "A dokumentumok összes tulajdonsága alapértelmezés szerint indexelve lesz a rugalmas és hatékony lekérdezések érdekében.",
      "indexingOffInfo": "Az indexelés ki lesz kapcsolva. Akkor ajánlott, ha nem kell lekérdezéseket futtatnia, vagy csak kulcsérték-műveletekkel rendelkezik.",
      "indexingOffWarning": "Ha úgy hozza létre ezt a tárolót, hogy az indexelés ki van kapcsolva, nem fogja tudni módosítani az indexelési szabályzatot. Az indexelési módosítások csak indexelési szabályzattal rendelkező tárolókon engedélyezettek.",
      "acknowledgeSpendErrorMonthly": "Nyugtázza a becsült havi ráfordítást.",
      "acknowledgeSpendErrorDaily": "Nyugtázza a becsült napi ráfordítást.",
      "unshardedMaxRuError": "A horizontálisan nem skálázott gyűjtemények legfeljebb 10 000 kérelemegységet támogatnak",
      "acknowledgeShareThroughputError": "Nyugtázza a dedikált átviteli sebesség becsült költségét.",
      "vectorPolicyError": "Javítsa ki a tároló vektorházirendjének hibáit",
      "fullTextSearchPolicyError": "Javítsa ki a tároló teljes szöveges keresési szabályzatának hibáit",
      "addingSampleDataSet": "Mintaadatkészlet hozzáadása",
      "databaseFieldLabelName": "Database name",
      "databaseFieldLabelId": "Database id",
      "newDatabaseIdPlaceholder": "Type a new database id",
      "newDatabaseIdAriaLabel": "New database id, Type a new database id",
      "createNewDatabaseAriaLabel": "Create new database",
      "useExistingDatabaseAriaLabel": "Use existing database",
      "chooseExistingDatabase": "Choose an existing database",
      "teachingBubble": {
        "step1Headline": "Create sample database",
        "step1Body": "Database is the parent of a container. You can create a new database or use an existing one. In this tutorial we are creating a new database named SampleDB.",
        "step1LearnMore": "Learn more about resources.",
        "step2Headline": "Setting throughput",
        "step2Body": "Cosmos DB recommends sharing throughput across database. Autoscale will give you a flexible amount of throughput based on the max RU/s set (Request Units).",
        "step2LearnMore": "Learn more about RU/s.",
        "step3Headline": "Naming container",
        "step3Body": "Name your container",
        "step4Headline": "Setting partition key",
        "step4Body": "Last step - you will need to define a partition key for your collection. /address was chosen for this particular example. A good partition key should have a wide range of possible value",
        "step4CreateContainer": "Create container",
        "step5Headline": "Creating sample container",
        "step5Body": "A sample container is now being created and we are adding sample data for you. It should take about 1 minute.",
        "step5BodyFollowUp": "Once the sample container is created, review your sample dataset and follow next steps",
        "stepOfTotal": "Step {{current}} of {{total}}"
      }
    },
    "addCollectionUtility": {
      "shardKeyTooltip": "A szegmenskulcs (mező) az adatok több replikakészletre (szegmensre) való felosztására szolgál a korlátlan méretezhetőség érdekében. Kritikus fontosságú olyan mezőt választani, amely egyenletesen osztja el az adatokat.",
      "partitionKeyTooltip": "A(z) {{partitionKeyName}} automatikusan elosztja az adatokat a partíciók között a méretezhetőség érdekében. Válasszon egy olyan tulajdonságot a JSON-dokumentumban, amely számos értékkel rendelkezik, és egyenletesen osztja el a kérések mennyiségét.",
      "partitionKeyTooltipSqlSuffix": " A kisméretű olvasásigényes, vagy bármilyen méretű írásigényes számítási feladatok esetében az azonosító gyakran jó választás.",
      "shardKeyLabel": "Szegmenskulcs",
      "partitionKeyLabel": "Partíciókulcs",
      "shardKeyPlaceholder": "például categoryId",
      "partitionKeyPlaceholderDefault": "például /address",
      "partitionKeyPlaceholderFirst": "Kötelező – első partíciókulcs, például /TenantId",
      "partitionKeyPlaceholderSecond": "második partíciókulcs, például /UserId",
      "partitionKeyPlaceholderThird": "harmadik partíciókulcs, például /SessionId",
      "partitionKeyPlaceholderGraph": "például, /address/zipCode",
      "uniqueKeysTooltip": "Az egyedi kulcsok lehetővé teszik a fejlesztők számára, hogy adatintegritási réteget adjanak az adatbázisukhoz. Egy tároló létrehozásakor egy egyedi kulcsszabályzat létrehozásával biztosítja egy vagy több érték egyediségét partíciókulcsonként.",
      "uniqueKeysLabel": "Egyedi kulcsok",
      "analyticalStoreLabel": "Elemzési tár",
      "analyticalStoreTooltip": "Engedélyezze az elemzési tár képességet, hogy közel valós idejű elemzéseket végezhessen az operatív adatokon anélkül, hogy az hatással lenne a tranzakciós számítási feladatok teljesítményére.",
      "analyticalStoreDescription": "Engedélyezze az elemzési tár képességet, hogy közel valós idejű elemzéseket végezhessen az operatív adatokon anélkül, hogy az hatással lenne a tranzakciós számítási feladatok teljesítményére.",
      "vectorPolicyTooltip": "Ismertesse az adataiban a vektorokat tartalmazó tulajdonságokat, hogy elérhetővé lehessen tenni azokat hasonlósági lekérdezésekhez."
    },
    "settings": {
      "pageOptions": "Lapbeállítások",
      "pageOptionsDescription": "Válassza az Egyéni lehetőséget a megjelenítendő lekérdezési eredmények rögzített mennyiségének megadásához, vagy válassza a Korlátlan lehetőséget, ha oldalanként annyi lekérdezési eredményt szeretne megjeleníteni.",
      "queryResultsPerPage": "Lekérdezési eredmények oldalanként",
      "queryResultsPerPageTooltip": "Adja meg az oldalanként megjelenítendő lekérdezési eredmények számát.",
      "customQueryItemsPerPage": "Egyéni lekérdezéselemek oldalanként",
      "custom": "Egyéni",
      "unlimited": "Korlátlan",
      "entraIdRbac": "Entra ID RBAC engedélyezése",
      "entraIdRbacDescription": "Válassza az Automatikus lehetőséget az Entra ID RBAC automatikus engedélyezéséhez. Igaz/Hamis az Entra ID RBAC engedélyezésének/letiltásának kényszerítéséhez.",
      "true": "Igaz",
      "false": "Hamis",
      "regionSelection": "Régió kiválasztása",
      "regionSelectionDescription": "A Cosmos-ügyfél által a fiók eléréséhez használt régiót módosítja.",
      "selectRegion": "Régió kiválasztása",
      "selectRegionTooltip": "Módosítja az ügyfélműveletek végrehajtásához használt fiókvégpontot.",
      "globalDefault": "Globális (alapértelmezett)",
      "readWrite": "(Olvasás/írás)",
      "read": "(Olvasás)",
      "queryTimeout": "Lekérdezés időkorlátja",
      "queryTimeoutDescription": "Ha egy lekérdezés eléri a megadott időkorlátot, megjelenik egy, a lekérdezés megszakítására szolgáló előugró ablak, kivéve, ha engedélyezve van az automatikus megszakítás.",
      "enableQueryTimeout": "Lekérdezés időtúllépésének engedélyezése",
      "queryTimeoutMs": "Lekérdezés időkorlátja (ms)",
      "automaticallyCancelQuery": "Lekérdezés automatikus megszakítása időtúllépés után",
      "ruLimit": "RU-korlát",
      "ruLimitDescription": "Ha egy lekérdezés túllépi a konfigurált RU-korlátot, a rendszer megszakítja a lekérdezést.",
      "enableRuLimit": "RU-korlát bekapcsolása",
      "ruLimitLabel": "RU-korlát (RU)",
      "defaultQueryResults": "Lekérdezési eredmények alapértelmezett nézete",
      "defaultQueryResultsDescription": "Válassza ki a lekérdezés eredményeinek megjelenítésekor használandó alapértelmezett nézetet.",
      "retrySettings": "Ismétlések beállításai",
      "retrySettingsDescription": "Szabályozott kérelmekhez társított újrapróbálkozási szabályzat a CosmosDB-lekérdezések során.",
      "maxRetryAttempts": "Újrapróbálkozások maximális száma",
      "maxRetryAttemptsTooltip": "A kérelmekhez végrehajtandó újrapróbálkozások maximális száma. Alapértelmezett érték: 9.",
      "fixedRetryInterval": "Rögzített újrapróbálkozási időköz (ms)",
      "fixedRetryIntervalTooltip": "Kijavítottuk az egyes újrapróbálkozások közötti várakozáshoz ezredmásodpercben megadott újrapróbálkozási időközt amely, figyelmen kívül hagyta a válasz részeként visszaadott retryAfter értéket. Az alapértelmezett érték 0 ezredmásodperc.",
      "maxWaitTime": "Maximális várakozási idő (s)",
      "maxWaitTimeTooltip": "Maximális várakozási idő másodpercben, amíg a rendszer egy kérelemre várakozik, amíg az újrapróbálkozások történnek. Alapértelmezett érték: 30 másodperc.",
      "enableContainerPagination": "Tároló oldalakra tördelésének engedélyezése",
      "enableContainerPaginationDescription": "Egyszerre 50 tároló betöltése. A tárolók lekérése jelenleg nem alfanumerikus sorrendben történik.",
      "enableCrossPartitionQuery": "Partíciók közötti lekérdezés engedélyezése",
      "enableCrossPartitionQueryDescription": "Lekérdezés végrehajtása során több kérés is küldhető. Egynél több kérésre van szükség, ha a lekérdezés hatóköre nincs egyetlen partíciókulcs-értékre korlátozva.",
      "maxDegreeOfParallelism": "Párhuzamosság maximális foka",
      "maxDegreeOfParallelismDescription": "Lekérdezi vagy beállítja az egyidejűleg futtatott műveletek számát az ügyféloldalon a párhuzamos lekérdezés-végrehajtás során. A pozitív tulajdonságérték az egyidejű műveletek számát a beállított értékre korlátozza. Ha 0-nál kisebb értékre van állítva, a rendszer automatikusan eldönti az egyidejű futtatandó műveletek számát.",
      "maxDegreeOfParallelismQuery": "Lekérdezés a párhuzamosság maximális mértékéig.",
      "priorityLevel": "Prioritásszint",
      "priorityLevelDescription": "Beállítja a prioritási szintet a Data Explorerből érkező adatsík-kérelmekhez prioritásalapú végrehajtás használatakor. Ha a Nincs érték van kiválasztva, a Data Explorer nem adja meg a prioritási szintet, és a kiszolgálóoldali alapértelmezett prioritási szintet fogja használni.",
      "displayGremlinQueryResults": "Gremlin-lekérdezés eredményeinek megjelenítése a következőként:",
      "displayGremlinQueryResultsDescription": "Válassza a Graph lehetőséget a lekérdezés eredményeinek automatikusan gráfként, vagy a JSON lehetőséget JSON-ként való megjelenítéséhez.",
      "graph": "Gráf",
      "json": "JSON",
      "graphAutoVisualization": "Gráf automatikus vizualizációja",
      "enableSampleDatabase": "Mintaadatbázis engedélyezése",
      "enableSampleDatabaseDescription": "Ez egy mintaadatbázis és -gyűjtemény szintetikus termékadatokkal, amelyeket NoSQL-lekérdezésekkel való felderítésre használhat. Ez egy másik adatbázisként jelenik meg a Data Explorer felhasználói felületén, amelyet a Microsoft hoz létre és tart karban díjmentesen.",
      "enableSampleDbAriaLabel": "Mintaadatbázis engedélyezése a lekérdezések feltárásához",
      "guidRepresentation": "GUID-ábrázolás",
      "guidRepresentationDescription": "A MongoDB GuidRepresentation tulajdonsága arra utal, hogy a globálisan egyedi azonosítók (GUID-ok) szerializálása és deszerializálása hogyan történik BSON-dokumentumokban való tárolás esetén. Ez minden dokumentumműveletre érvényes lesz.",
      "advancedSettings": "Speciális beállítások",
      "ignorePartitionKey": "Partíciókulcs figyelmen kívül hagyása a dokumentum frissítésekor",
      "ignorePartitionKeyTooltip": "Ha be van jelölve, a rendszer nem használja a partíciókulcs értékét a dokumentum megkereséséhez a frissítési műveletek során. Csak akkor használja, ha a dokumentumfrissítések rendellenes partíciókulcs miatt meghiúsulnak.",
      "clearHistory": "Előzmények törlése",
      "clearHistoryConfirm": "Biztosan folytatja?",
      "clearHistoryDescription": "Ez a művelet törli a fiók összes testreszabását ebben a böngészőben, beleértve a következőket:",
      "clearHistoryTabLayout": "A testre szabott lapelrendezés alaphelyzetbe állítása, beleértve az elválasztóhelyeket is",
      "clearHistoryTableColumns": "A táblázat oszlopbeállításainak törlése, beleértve az egyéni oszlopokat is",
      "clearHistoryFilters": "Szűrőelőzmények törlése",
      "clearHistoryRegion": "Régiókiválasztás visszaállítása globálisra",
      "increaseValueBy1000": "Érték növelése 1000-rel",
      "decreaseValueBy1000": "Érték csökkentése 1000-rel",
      "none": "Nincs",
      "low": "Alacsony",
      "high": "Magas",
      "automatic": "Automatikus",
      "enhancedQueryControl": "Továbbfejlesztett lekérdezésvezérlő",
      "enableQueryControl": "Lekérdezésvezérlő engedélyezése",
      "explorerVersion": "Explorer verziója",
      "accountId": "Fiókazonosító",
      "sessionId": "Munkamenet-azonosító",
      "popupsDisabledError": "Nem sikerült hitelesítést létrehozni ehhez a fiókhoz, mert a böngészőben le vannak tiltva az előugró ablakok.\nEngedélyezze az előugró ablakokat ehhez a webhelyhez, majd kattintson az Entra ID bejelentkezés gombra",
      "failedToAcquireTokenError": "Nem sikerült automatikusan beszerezni az engedélyezési jogkivonatot. Kattintson az Entra ID bejelentkezés gombra az Entra ID RBAC-műveletek engedélyezéséhez"
    },
    "saveQuery": {
      "panelTitle": "Lekérdezés mentése",
      "setupCostMessage": "Megfelelőségi okokból a lekérdezéseket egy tárolóba mentjük az Azure Cosmos-fiókjában, egy különálló, {{databaseName}} nevű adatbázisban. A folytatáshoz létre kell hoznunk egy tárolót a fiókjában. A becsült további költség naponta 0,77 USD.",
      "completeSetup": "Beállítás befejezése",
      "noQueryNameError": "Nincs megadva lekérdezésnév",
      "invalidQueryContentError": "Érvénytelen lekérdezési tartalom megadva",
      "failedToSaveQueryError": "A(z) {{queryName}} lekérdezés mentése nem sikerült",
      "failedToSetupContainerError": "Nem sikerült beállítani tárolót a mentett lekérdezésekhez",
      "accountNotSetupError": "Nem sikerült menteni a lekérdezést: a fiók nincs beállítva a lekérdezések mentéséhez",
      "name": "Név"
    },
    "loadQuery": {
      "noFileSpecifiedError": "Nincs megadva fájl",
      "failedToLoadQueryError": "Nem sikerült betölteni a lekérdezést",
      "failedToLoadQueryFromFileError": "Nem sikerült betölteni a lekérdezést (z) {{fileName}} fájlból",
      "selectFilesToOpen": "Lekérdezési dokumentum kiválasztása",
      "browseFiles": "Tallózás"
    },
    "executeStoredProcedure": {
      "enterInputParameters": "Adja meg a bemeneti paramétereket (ha vannak ilyenek)",
      "key": "Kulcs",
      "param": "Paraméter",
      "partitionKeyValue": "Partíciókulcs értéke",
      "value": "Érték",
      "addNewParam": "Új paraméter hozzáadása",
      "addParam": "Paraméter hozzáadása",
      "deleteParam": "Paraméter törlése",
      "invalidParamError": "Érvénytelen paraméter megadva: {{invalidParam}}",
      "invalidParamConsoleError": "Érvénytelen paraméter megadva: a(z) {{invalidParam}} nem érvényes konstansérték",
      "stringType": "Sztring",
      "customType": "Egyéni"
    },
    "uploadItems": {
      "noFilesSpecifiedError": "Nincs megadva fájl. Adjon meg legalább egy fájlt.",
      "selectJsonFiles": "JSON-fájlok kiválasztása",
      "selectJsonFilesTooltip": "Jelöljön ki egy vagy több feltöltendő JSON-fájlt. Minden fájl egyetlen JSON-dokumentumot vagy egy JSON-dokumentumtömböt tartalmazhat. Az egyes feltöltési műveletek összes fájljának összesített méretének 2 MB alatt kell lennie. Nagyobb adatkészletek esetében több feltöltési műveletet is végrehajthat.",
      "fileNameColumn": "FÁJLNÉV",
      "statusColumn": "ÁLLAPOT",
      "uploadStatus": "{{numSucceeded}} létrehozva, {{numThrottled}} szabályozva, {{numFailed}} hiba",
      "uploadedFiles": "Feltöltött fájlok"
    },
    "copyNotebook": {
      "copyFailedError": "Nem sikerült a(z) {{name}} másolása ide: {{destination}}",
      "uploadFailedError": "Nem sikerült a(z) {{name}} feltöltése",
      "location": "Hely",
      "locationAriaLabel": "Hely",
      "selectLocation": "Jegyzetfüzet másolási helyének kiválasztása",
      "name": "Név"
    },
    "publishNotebook": {
      "publishFailedError": "Nem sikerült a(z) {{notebookName}} közzététele a katalógusban",
      "publishDescription": "Közzétételkor ez a jegyzetfüzet megjelenik a Azure Cosmos DB jegyzetfüzetek nyilvános katalógusában. A közzététel előtt győződjön meg arról, hogy eltávolította a bizalmas adatokat vagy kimeneteket.",
      "publishPrompt": "Közzéteszi és megosztja a(z) {{name}} dokumentumot a katalógusban?",
      "coverImage": "Borítókép",
      "coverImageUrl": "Borítókép URL-címe",
      "name": "Név",
      "description": "Leírás",
      "tags": "Címkék",
      "tagsPlaceholder": "Nem kötelező címke 1, nem kötelező címke 2",
      "preview": "Előzetes verzió",
      "urlType": "URL-cím",
      "customImage": "Egyéni rendszerkép",
      "takeScreenshot": "Képernyőkép készítése",
      "useFirstDisplayOutput": "Első megjelenítési kimenet használata",
      "failedToCaptureOutput": "Nem sikerült rögzíteni az első kimenetet",
      "outputDoesNotExist": "A kimenet nem létezik egyik cellához sem.",
      "failedToConvertError": "Nem sikerült a(z) {{fileName}} base64 formátumra való konvertálása",
      "failedToUploadError": "Nem sikerült a(z) {{fileName}} feltöltése"
    },
    "changePartitionKey": {
      "failedToStartError": "Nem sikerült elindítani az adatátviteli feladatot",
      "suboptimalPartitionKeyError": "Figyelmeztetés: A rendszer úgy észlelte, hogy a gyűjtemény valószínűleg nem optimális partíciókulcsot használ",
      "description": "A tároló partíciókulcsának módosításakor létre kell hoznia egy céltárolót a megfelelő partíciókulccsal. Kiválaszthat egy meglévő céltárolót is.",
      "sourceContainerId": "Forrás {{collectionName}}-azonosítója",
      "destinationContainerId": "Cél {{collectionName}}-azonosítója",
      "collectionIdTooltip": "A(z) {{collectionName}} egyedi azonosítója, amelyet a rendszer az azonosítóalapú útválasztás során használ a REST-ben és az összes SDK-ban.",
      "collectionIdPlaceholder": "például {{collectionName}}1",
      "collectionIdAriaLabel": "{{collectionName}}-azonosító, {{collectionName}}1. példa",
      "existingContainers": "Meglévő tárolók",
      "partitionKeyWarning": "A céltároló még nem létezhet. A Data Explorer egy új céltárolót hoz létre."
    },
    "cassandraAddCollection": {
      "keyspaceLabel": "Kulcstér neve",
      "keyspaceTooltip": "Válasszon ki egy meglévő kulcsteret, vagy adjon meg egy új kulcstér-azonosítót.",
      "tableIdLabel": "A tábla létrehozásához írja be a CQL parancsot.",
      "enterTableId": "Táblaazonosító megadása",
      "tableSchemaAriaLabel": "Táblaséma",
      "provisionDedicatedThroughput": "Dedikált átviteli sebesség kiépítése ehhez a táblához",
      "provisionDedicatedThroughputTooltip": "Opcionálisan dedikált átviteli sebességet is kioszthat egy táblához egy kiépített átviteli sebességgel rendelkező kulcstéren belül. Ez a dedikált átviteli sebesség nem lesz megosztva a kulcstér más tábláival, és nem számít bele a kulcstérhez kiosztott átviteli sebességbe. Ezt az átviteli sebességet a kulcstér szintjén kiosztott átviteli sebességen felül számlázzuk."
    },
    "tables": {
      "addProperty": "Tulajdonság hozzáadása",
      "addRow": "Sor hozzáadása",
      "addEntity": "Entitás hozzáadása",
      "back": "vissza",
      "nullFieldsWarning": "Figyelmeztetés: A null értékű mezők nem jelennek meg szerkesztésre.",
      "propertyEmptyError": "A(z) {{property}} nem lehet üres. Adjon meg egy értéket a(z) {{property}} tulajdonsághoz",
      "whitespaceError": "a(z) {{property}} nem rendelkezhet szóközzel. Adjon meg egy szóköz nélküli értéket a(z) {{property}} számára",
      "propertyTypeEmptyError": "A tulajdonságtípus nem lehet üres. Válasszon típust a(z) {{property}}tulajdonság legördülő listájából"
    },
    "tableQuerySelect": {
      "selectColumns": "Válassza ki a lekérdezni kívánt oszlopokat.",
      "availableColumns": "Elérhető oszlopok"
    },
    "tableColumnSelection": {
      "selectColumns": "Válassza ki, hogy mely oszlopok jelenjenek meg a tároló elemeinek nézetében.",
      "searchFields": "Mezők keresése",
      "reset": "Alaphelyzetbe állítás",
      "partitionKeySuffix": " (partíciókulcs)"
    },
    "newVertex": {
      "addProperty": "Tulajdonság hozzáadása"
    },
    "addGlobalSecondaryIndex": {
      "globalSecondaryIndexId": "Globális másodlagos index tárolóazonosítója",
      "globalSecondaryIndexIdPlaceholder": "például indexbyEmailId",
      "projectionQuery": "Leképezési lekérdezés",
      "projectionQueryPlaceholder": "SELECT c.email, c.accountId FROM c",
      "projectionQueryTooltip": "További információ a globális másodlagos indexek definiálásáról.",
      "disabledTitle": "Már folyamatban van egy globális másodlagos index létrehozása. Várja meg, amíg befejeződik, mielőtt egy másikat hozna létre."
    },
    "stringInput": {
      "inputMismatchError": "A(z) {{input}} bemenet nem egyezik a kijelölt {{selectedId}} értékével"
    },
    "panelInfo": {
      "information": "Információ",
      "moreDetails": "További részletek"
    }
  },
  "controls": {
    "settings": {
      "tabTitles": {
        "scale": "Scale",
        "conflictResolution": "Conflict Resolution",
        "settings": "Settings",
        "indexingPolicy": "Indexing Policy",
        "partitionKeys": "Partition Keys",
        "partitionKeysPreview": "Partition Keys (preview)",
        "computedProperties": "Computed Properties",
        "containerPolicies": "Container Policies",
        "throughputBuckets": "Throughput Buckets",
        "globalSecondaryIndexPreview": "Global Secondary Index (Preview)",
        "maskingPolicyPreview": "Masking Policy (preview)"
      },
      "mongoNotifications": {
        "selectTypeWarning": "Please select a type for each index.",
        "enterFieldNameError": "Adjon meg egy mezőnevet.",
        "wildcardPathError": "Wildcard path is not present in the field name. Use a pattern like "
      },
      "partitionKey": {
        "shardKey": "Shard key",
        "partitionKey": "Partition key",
        "shardKeyTooltip": "A szegmenskulcs (mező) az adatok több replikakészletre (szegmensre) való felosztására szolgál a korlátlan méretezhetőség érdekében. Kritikus fontosságú olyan mezőt választani, amely egyenletesen osztja el az adatokat.",
        "partitionKeyTooltip": "is used to automatically distribute data across partitions for scalability. Choose a property in your JSON document that has a wide range of values and evenly distributes request volume.",
        "sqlPartitionKeyTooltipSuffix": " A kisméretű olvasásigényes, vagy bármilyen méretű írásigényes számítási feladatok esetében az azonosító gyakran jó választás.",
        "partitionKeySubtext": "For small workloads, the item ID is a suitable choice for the partition key.",
        "mongoPlaceholder": "e.g., categoryId",
        "gremlinPlaceholder": "e.g., /address",
        "sqlFirstPartitionKey": "Kötelező – első partíciókulcs, például /TenantId",
        "sqlSecondPartitionKey": "második partíciókulcs, például /UserId",
        "sqlThirdPartitionKey": "harmadik partíciókulcs, például /SessionId",
        "defaultPlaceholder": "e.g., /address/zipCode"
      },
      "costEstimate": {
        "title": "Cost estimate*",
        "howWeCalculate": "How we calculate this",
        "updatedCostPerMonth": "Updated cost per month",
        "currentCostPerMonth": "Current cost per month",
        "perRu": "/RU",
        "perHour": "/hr",
        "perDay": "/day",
        "perMonth": "/mo"
      },
      "throughput": {
        "manualToAutoscaleDisclaimer": "The starting autoscale max RU/s will be determined by the system, based on the current manual throughput settings and storage of your resource. After autoscale has been enabled, you can change the max RU/s.",
        "ttlWarningText": "The system will automatically delete items based on the TTL value (in seconds) you provide, without needing a delete operation explicitly issued by a client application. For more information see,",
        "ttlWarningLinkText": "Time to Live (TTL) in Azure Cosmos DB",
        "unsavedIndexingPolicy": "indexing policy",
        "unsavedDataMaskingPolicy": "data masking policy",
        "unsavedComputedProperties": "computed properties",
        "unsavedEditorWarningPrefix": "You have not saved the latest changes made to your",
        "unsavedEditorWarningSuffix": ". Please click save to confirm the changes.",
        "updateDelayedApplyWarning": "You are about to request an increase in throughput beyond the pre-allocated capacity. This operation will take some time to complete.",
        "scalingUpDelayMessage": "Scaling up will take 4-6 hours as it exceeds what Azure Cosmos DB can instantly support currently based on your number of physical partitions. You can increase your throughput to {{instantMaximumThroughput}} instantly or proceed with this value and wait until the scale-up is completed.",
        "exceedPreAllocatedMessage": "Your request to increase throughput exceeds the pre-allocated capacity which may take longer than expected. There are three options you can choose from to proceed:",
        "instantScaleOption": "You can instantly scale up to {{instantMaximumThroughput}} RU/s.",
        "asyncScaleOption": "You can asynchronously scale up to any value under {{maximumThroughput}} RU/s in 4-6 hours.",
        "quotaMaxOption": "Your current quota max is {{maximumThroughput}} RU/s. To go over this limit, you must request a quota increase and the Azure Cosmos DB team will review.",
        "belowMinimumMessage": "You are not able to lower throughput below your current minimum of {{minimum}} RU/s. For more information on this limit, please refer to our service quote documentation.",
        "saveThroughputWarning": "Your bill will be affected as you update your throughput settings. Please review the updated cost estimate below before saving your changes",
        "currentAutoscaleThroughput": "Current autoscale throughput:",
        "targetAutoscaleThroughput": "Target autoscale throughput:",
        "currentManualThroughput": "Current manual throughput:",
        "targetManualThroughput": "Target manual throughput:",
        "applyDelayedMessage": "The request to increase the throughput has successfully been submitted. This operation will take 1-3 business days to complete. View the latest status in Notifications.",
        "databaseLabel": "Database:",
        "containerLabel": "Container:",
        "applyShortDelayMessage": "A request to increase the throughput is currently in progress. This operation will take some time to complete.",
        "applyLongDelayMessage": "A request to increase the throughput is currently in progress. This operation will take 1-3 business days to complete. View the latest status in Notifications.",
        "throughputCapError": "Your account is currently configured with a total throughput limit of {{throughputCap}} RU/s. This update isn't possible because it would increase the total throughput to {{newTotalThroughput}} RU/s. Change total throughput limit in cost management.",
        "throughputIncrementError": "Throughput value must be in increments of 1000"
      },
      "conflictResolution": {
        "lwwDefault": "Last Write Wins (default)",
        "customMergeProcedure": "Merge Procedure (custom)",
        "mode": "Mode",
        "conflictResolverProperty": "Conflict Resolver Property",
        "storedProcedure": "Stored procedure",
        "lwwTooltip": "Gets or sets the name of a integer property in your documents which is used for the Last Write Wins (LWW) based conflict resolution scheme. By default, the system uses the system defined timestamp property, _ts to decide the winner for the conflicting versions of the document. Specify your own integer property if you want to override the default timestamp based conflict resolution.",
        "customTooltip": "Gets or sets the name of a stored procedure (aka merge procedure) for resolving the conflicts. You can write application defined logic to determine the winner of the conflicting versions of a document. The stored procedure will get executed transactionally, exactly once, on the server side. If you do not provide a stored procedure, the conflicts will be populated in the",
        "customTooltipConflictsFeed": " conflicts feed",
        "customTooltipSuffix": ". You can update/re-register the stored procedure at any time."
      },
      "changeFeed": {
        "label": "Change feed log retention policy",
        "tooltip": "Enable change feed log retention policy to retain last 10 minutes of history for items in the container by default. To support this, the request unit (RU) charge for this container will be multiplied by a factor of two for writes. Reads are unaffected."
      },
      "mongoIndexing": {
        "disclaimer": "For queries that filter on multiple properties, create multiple single field indexes instead of a compound index.",
        "disclaimerCompoundIndexesLink": " Compound indexes ",
        "disclaimerSuffix": "are only used for sorting query results. If you need to add a compound index, you can create one using the Mongo shell.",
        "compoundNotSupported": "Collections with compound indexes are not yet supported in the indexing editor. To modify indexing policy for this collection, use the Mongo Shell.",
        "aadError": "To use the indexing policy editor, please login to the",
        "aadErrorLink": "azure portal.",
        "refreshingProgress": "Refreshing index transformation progress",
        "canMakeMoreChangesZero": "You can make more indexing changes once the current index transformation is complete. ",
        "refreshToCheck": "Refresh to check if it has completed.",
        "canMakeMoreChangesProgress": "You can make more indexing changes once the current index transformation has completed. It is {{progress}}% complete. ",
        "refreshToCheckProgress": "Refresh to check the progress.",
        "definitionColumn": "Definition",
        "typeColumn": "Type",
        "dropIndexColumn": "Drop Index",
        "addIndexBackColumn": "Add index back",
        "deleteIndexButton": "Delete index Button",
        "addBackIndexButton": "Add back Index Button",
        "currentIndexes": "Current index(es)",
        "indexesToBeDropped": "Index(es) to be dropped",
        "indexFieldName": "Index Field Name",
        "indexType": "Index Type",
        "selectIndexType": "Select an index type",
        "undoButton": "Undo Button"
      },
      "subSettings": {
        "timeToLive": "Time to Live",
        "ttlOff": "Off",
        "ttlOnNoDefault": "On (no default)",
        "ttlOn": "On",
        "seconds": "second(s)",
        "timeToLiveInSeconds": "Time to live in seconds",
        "analyticalStorageTtl": "Analytical Storage Time to Live",
        "geospatialConfiguration": "Geospatial Configuration",
        "geography": "Geography",
        "geometry": "Geometry",
        "uniqueKeys": "Unique keys",
        "mongoTtlMessage": "To enable time-to-live (TTL) for your collection/documents,",
        "mongoTtlLinkText": "create a TTL index",
        "partitionKeyTooltipTemplate": "This {{partitionKeyName}} is used to distribute data across multiple partitions for scalability. The value \"{{partitionKeyValue}}\" determines how documents are partitioned.",
        "largePartitionKeyEnabled": "Large {{partitionKeyName}} has been enabled.",
        "hierarchicalPartitioned": "Hierarchically partitioned container.",
        "nonHierarchicalPartitioned": "Non-hierarchically partitioned container."
      },
      "scale": {
        "freeTierInfo": "With free tier, you will get the first {{ru}} RU/s and {{storage}} GB of storage in this account for free. To keep your account free, keep the total RU/s across all resources in the account to {{ru}} RU/s.",
        "freeTierLearnMore": "Learn more.",
        "throughputRuS": "Throughput (RU/s)",
        "autoScaleCustomSettings": "Your account has custom settings that prevents setting throughput at the container level. Please work with your Cosmos DB engineering team point of contact to make changes.",
        "keyspaceSharedThroughput": "This table shared throughput is configured at the keyspace",
        "throughputRangeLabel": "Throughput ({{min}} - {{max}} RU/s)",
        "unlimited": "unlimited"
      },
      "partitionKeyEditor": {
        "changePartitionKey": "Change {{partitionKeyName}}",
        "currentPartitionKey": "Current {{partitionKeyName}}",
        "partitioning": "Partitioning",
        "hierarchical": "Hierarchical",
        "nonHierarchical": "Non-hierarchical",
        "safeguardWarning": "To safeguard the integrity of the data being copied to the new container, ensure that no updates are made to the source container for the entire duration of the partition key change process.",
        "changeDescription": "To change the partition key, a new destination container must be created or an existing destination container selected. Data will then be copied to the destination container.",
        "changeButton": "Change",
        "changeJob": "{{partitionKeyName}} change job",
        "cancelButton": "Cancel",
        "documentsProcessed": "({{processedCount}} of {{totalCount}} documents processed)"
      },
      "computedProperties": {
        "ariaLabel": "Computed properties",
        "learnMorePrefix": "about how to define computed properties and how to use them."
      },
      "indexingPolicy": {
        "ariaLabel": "Indexing Policy"
      },
      "dataMasking": {
        "ariaLabel": "Data Masking Policy",
        "validationFailed": "Validation failed:",
        "includedPathsRequired": "includedPaths is required",
        "includedPathsMustBeArray": "includedPaths must be an array",
        "excludedPathsMustBeArray": "excludedPaths must be an array if provided"
      },
      "containerPolicy": {
        "vectorPolicy": "Vector Policy",
        "fullTextPolicy": "Full Text Policy",
        "createFullTextPolicy": "Create new full text search policy"
      },
      "globalSecondaryIndex": {
        "indexesDefined": "This container has the following indexes defined for it.",
        "learnMoreSuffix": "about how to define global secondary indexes and how to use them.",
        "jsonAriaLabel": "Global Secondary Index JSON",
        "addIndex": "Add index",
        "settingsTitle": "Global Secondary Index Settings",
        "sourceContainer": "Source container",
        "indexDefinition": "Global secondary index definition"
      },
      "indexingPolicyRefresh": {
        "refreshFailed": "Refreshing index transformation progress failed"
      },
      "throughputInput": {
        "autoscale": "Autoscale",
        "manual": "Manual",
        "minimumRuS": "Minimum RU/s",
        "maximumRuS": "Maximum RU/s",
        "x10Equals": "x 10 =",
        "storageCapacity": "Storage capacity",
        "fixed": "Fixed",
        "unlimited": "Unlimited",
        "instant": "Instant",
        "fourToSixHrs": "4-6 hrs",
        "autoscaleDescription": "Based on usage, your {{resourceType}} throughput will scale from",
        "freeTierWarning": "Billing will apply if you provision more than {{ru}} RU/s of manual throughput, or if the resource scales beyond {{ru}} RU/s with autoscale.",
        "capacityCalculator": "Estimate your required RU/s with",
        "capacityCalculatorLink": " capacity calculator",
        "fixedStorageNote": "When using a collection with fixed storage capacity, you can set up to 10,000 RU/s.",
        "min": "min",
        "max": "max"
      },
      "throughputBuckets": {
        "label": "Throughput Buckets",
        "bucketLabel": "Bucket {{id}}",
        "dataExplorerQueryBucket": " (Data Explorer Query Bucket)",
        "active": "Active",
        "inactive": "Inactive"
      }
    }
  }
}